pycmd/Command.py
pycmd/__init__.py
pycmd/cli.py
pycmd/environ.py
pycmd/executor.py
pycmd/help.py
pycmd/program.py
pycmd/utils.py
pycmd/windows/01.py
pycmd/windows/demo.py
pyshellx-1.0.7.dist-info/METADATA
pyshellx-1.0.7.dist-info/WHEEL
pyshellx-1.0.7.dist-info/entry_points.txt
pyshellx-1.0.7.dist-info/top_level.txt
pyshellx-1.0.7.dist-info/RECORD
